anidbcli
