Metadata-Version: 1.1
Name: anidbcli
Version: 1.40
Summary: Simple CLI for managing your anime collection using AniDB UDP API.
Home-page: https://github.com/adameste/anidbcli
Author: Štěpán Adámek
Author-email: adamek.stepan@gmail.com
License: MIT
Keywords: Anidb UDP API CLI client ed2k rename mylist
Platform: UNKNOWN
Classifier: Development Status :: 5 - Production/Stable
Classifier: Environment :: Console
Classifier: Intended Audience :: End Users/Desktop
Classifier: License :: OSI Approved :: MIT License
Classifier: Natural Language :: English
Classifier: Programming Language :: Python
Classifier: Programming Language :: Python :: 3
Classifier: Programming Language :: Python :: 3.5
Classifier: Programming Language :: Python :: 3.6
Classifier: Topic :: Utilities
Classifier: Topic :: Multimedia :: Video
